Metadata-Version: 2.1
Name: manim-web-physics
Version: 0.1.0
Summary: A fork of Manim Physics for Manim Web
Home-page: https://github.com/MathItYT/manim-physics
Author: MathItYT
Author-email: benjamin.ubilla@uc.cl
Requires-Python: >=3.10,<3.14
Classifier: Programming Language :: Python :: 3
Classifier: Programming Language :: Python :: 3.10
Classifier: Programming Language :: Python :: 3.11
Classifier: Programming Language :: Python :: 3.12
Classifier: Programming Language :: Python :: 3.13
Requires-Dist: manim-web (>=0.1.7)
Requires-Dist: shapely (>=2.0,<=2.0.6)
Project-URL: Repository, https://github.com/MathItYT/manim-physics
